ecs_logging/__init__.py
ecs_logging/_meta.py
ecs_logging/_stdlib.py
ecs_logging/_structlog.py
ecs_logging/_utils.py
ecs_logging/py.typed
ecs_logging-2.0.2.dist-info/WHEEL
ecs_logging-2.0.2.dist-info/METADATA
ecs_logging-2.0.2.dist-info/RECORD
