Metadata-Version: 2.1
Name: ecs-logging
Version: 2.0.2
Summary: Logging formatters for ECS (Elastic Common Schema) in Python
Home-page: https://github.com/elastic/ecs-logging-python
Author: Seth Michael Larson
Author-email: seth.larson@elastic.co
Requires-Python: >=3.6
Classifier: Development Status :: 5 - Production/Stable
Classifier: Intended Audience :: Developers
Classifier: Programming Language :: Python :: 3
Classifier: Programming Language :: Python :: 3.6
Classifier: Programming Language :: Python :: 3.7
Classifier: Programming Language :: Python :: 3.8
Classifier: Programming Language :: Python :: 3.9
Classifier: Programming Language :: Python :: 3.10
Classifier: Topic :: System :: Logging
Classifier: License :: OSI Approved :: Apache Software License
Requires-Dist: backports.functools-lru-cache; python_version < '3.3'
Requires-Dist: pytest ; extra == "develop"
Requires-Dist: pytest-cov ; extra == "develop"
Requires-Dist: mock ; extra == "develop"
Requires-Dist: structlog ; extra == "develop"
Requires-Dist: elastic-apm ; extra == "develop"
Project-URL: Changelog, https://github.com/elastic/ecs-logging-python/blob/main/CHANGELOG.md
Project-URL: Documentation, https://github.com/elastic/ecs-logging-python
Project-URL: Download, https://github.com/elastic/ecs-logging-python/releases
Project-URL: Issue Tracker, https://github.com/elastic/ecs-logging-python/issues
Project-URL: Source, https://github.com/elastic/ecs-logging-python
Provides-Extra: develop
